{"dobra":0,"indice":0,"SI-SDR_media_foreground_background":7.0180249214,"foreground.SI-SDR":3.2129641413,"background.SI-SDR":10.8230860837}
{"dobra":0,"indice":4,"SI-SDR_media_foreground_background":3.9474134445,"foreground.SI-SDR":2.1965914134,"background.SI-SDR":5.6982353318}
{"dobra":0,"indice":11,"SI-SDR_media_foreground_background":7.7248477936,"foreground.SI-SDR":6.548398436,"background.SI-SDR":8.9012970534}
{"dobra":0,"indice":18,"SI-SDR_media_foreground_background":-1.242713213,"foreground.SI-SDR":2.2728099194,"background.SI-SDR":-4.7582362908}
{"dobra":0,"indice":19,"SI-SDR_media_foreground_background":6.4520287514,"foreground.SI-SDR":5.1628817933,"background.SI-SDR":7.7411761516}
{"dobra":0,"indice":29,"SI-SDR_media_foreground_background":4.5213894844,"foreground.SI-SDR":-2.6862068411,"background.SI-SDR":11.7289856823}
{"dobra":0,"indice":31,"SI-SDR_media_foreground_background":4.090651989,"foreground.SI-SDR":-0.1207106427,"background.SI-SDR":8.3020143232}
{"dobra":0,"indice":33,"SI-SDR_media_foreground_background":1.1084753275,"foreground.SI-SDR":2.2234253944,"background.SI-SDR":-0.0064748554}
{"dobra":0,"indice":34,"SI-SDR_media_foreground_background":5.3818283081,"foreground.SI-SDR":0.2921744787,"background.SI-SDR":10.4714823799}
{"dobra":0,"indice":35,"SI-SDR_media_foreground_background":1.1191190481,"foreground.SI-SDR":-3.7820472435,"background.SI-SDR":6.0202852801}
{"dobra":0,"indice":38,"SI-SDR_media_foreground_background":5.2250289917,"foreground.SI-SDR":5.3509599174,"background.SI-SDR":5.0990977832}
{"dobra":0,"indice":39,"SI-SDR_media_foreground_background":3.9036159515,"foreground.SI-SDR":0.8444826459,"background.SI-SDR":6.9627493487}
{"dobra":0,"indice":44,"SI-SDR_media_foreground_background":6.3940758705,"foreground.SI-SDR":1.0504277038,"background.SI-SDR":11.737723807}
{"dobra":0,"indice":51,"SI-SDR_media_foreground_background":4.9773955345,"foreground.SI-SDR":5.5857108176,"background.SI-SDR":4.3690802114}
{"dobra":0,"indice":58,"SI-SDR_media_foreground_background":9.2229042053,"foreground.SI-SDR":7.1321329089,"background.SI-SDR":11.3136747392}
{"dobra":0,"indice":62,"SI-SDR_media_foreground_background":3.9688780308,"foreground.SI-SDR":-3.4083636283,"background.SI-SDR":11.3461196855}
{"dobra":0,"indice":67,"SI-SDR_media_foreground_background":3.2216403484,"foreground.SI-SDR":-2.2453010251,"background.SI-SDR":8.6885818129}
{"dobra":0,"indice":69,"SI-SDR_media_foreground_background":8.6836328506,"foreground.SI-SDR":7.8087943936,"background.SI-SDR":9.5584720745}
{"dobra":0,"indice":78,"SI-SDR_media_foreground_background":5.4076342583,"foreground.SI-SDR":2.3939904448,"background.SI-SDR":8.4212777513}
{"dobra":0,"indice":88,"SI-SDR_media_foreground_background":6.9170556068,"foreground.SI-SDR":2.9008544994,"background.SI-SDR":10.9332564188}
{"dobra":0,"indice":89,"SI-SDR_media_foreground_background":6.4008841515,"foreground.SI-SDR":4.9923104561,"background.SI-SDR":7.8094581072}
{"dobra":0,"indice":91,"SI-SDR_media_foreground_background":4.0554594994,"foreground.SI-SDR":1.3381678947,"background.SI-SDR":6.7727509793}
{"dobra":0,"indice":106,"SI-SDR_media_foreground_background":2.2715144157,"foreground.SI-SDR":-1.4605779781,"background.SI-SDR":6.0036070126}
{"dobra":0,"indice":112,"SI-SDR_media_foreground_background":3.2032015324,"foreground.SI-SDR":-0.3736959061,"background.SI-SDR":6.7800989385}
{"dobra":0,"indice":114,"SI-SDR_media_foreground_background":6.1797418594,"foreground.SI-SDR":2.9034599166,"background.SI-SDR":9.456023593}
{"dobra":0,"indice":116,"SI-SDR_media_foreground_background":3.0841372013,"foreground.SI-SDR":-0.1706491038,"background.SI-SDR":6.3389236028}
{"dobra":0,"indice":119,"SI-SDR_media_foreground_background":6.782875061,"foreground.SI-SDR":3.0402674607,"background.SI-SDR":10.5254822636}
{"dobra":0,"indice":122,"SI-SDR_media_foreground_background":-0.845339179,"foreground.SI-SDR":-0.6466219651,"background.SI-SDR":-1.0440564332}
{"dobra":0,"indice":138,"SI-SDR_media_foreground_background":4.2625546455,"foreground.SI-SDR":3.8085738648,"background.SI-SDR":4.7165349976}
{"dobra":0,"indice":148,"SI-SDR_media_foreground_background":5.0677461624,"foreground.SI-SDR":1.552971381,"background.SI-SDR":8.5825214039}
{"dobra":0,"indice":150,"SI-SDR_media_foreground_background":1.7530829906,"foreground.SI-SDR":-2.0398239149,"background.SI-SDR":5.5459899814}
{"dobra":0,"indice":154,"SI-SDR_media_foreground_background":2.3657672405,"foreground.SI-SDR":2.0651020255,"background.SI-SDR":2.6664324447}
{"dobra":0,"indice":160,"SI-SDR_media_foreground_background":1.1162126064,"foreground.SI-SDR":-0.5648524526,"background.SI-SDR":2.7972775574}
{"dobra":0,"indice":162,"SI-SDR_media_foreground_background":0.1816564351,"foreground.SI-SDR":1.9791774239,"background.SI-SDR":-1.6158645542}
{"dobra":0,"indice":169,"SI-SDR_media_foreground_background":7.9937696457,"foreground.SI-SDR":3.3060312354,"background.SI-SDR":12.6815080409}
{"dobra":0,"indice":171,"SI-SDR_media_foreground_background":2.7754371166,"foreground.SI-SDR":-2.5390006145,"background.SI-SDR":8.0898747392}
{"dobra":0,"indice":177,"SI-SDR_media_foreground_background":3.8457832336,"foreground.SI-SDR":1.1524397255,"background.SI-SDR":6.5391269433}
{"dobra":0,"indice":197,"SI-SDR_media_foreground_background":1.7181969881,"foreground.SI-SDR":4.0803677148,"background.SI-SDR":-0.6439736446}
{"dobra":0,"indice":200,"SI-SDR_media_foreground_background":1.2596904039,"foreground.SI-SDR":3.6387712754,"background.SI-SDR":-1.119390565}
{"dobra":0,"indice":210,"SI-SDR_media_foreground_background":2.0857875347,"foreground.SI-SDR":-4.149651887,"background.SI-SDR":8.3212269023}
{"dobra":0,"indice":211,"SI-SDR_media_foreground_background":6.6966733932,"foreground.SI-SDR":5.4147030658,"background.SI-SDR":7.9786434273}
{"dobra":0,"indice":218,"SI-SDR_media_foreground_background":5.0441789627,"foreground.SI-SDR":3.4327231956,"background.SI-SDR":6.6556347033}
{"dobra":0,"indice":220,"SI-SDR_media_foreground_background":7.2108440399,"foreground.SI-SDR":6.7183820607,"background.SI-SDR":7.7033060276}
{"dobra":0,"indice":222,"SI-SDR_media_foreground_background":4.7766838074,"foreground.SI-SDR":2.288751302,"background.SI-SDR":7.264616439}
{"dobra":0,"indice":225,"SI-SDR_media_foreground_background":3.0505735874,"foreground.SI-SDR":0.4175338403,"background.SI-SDR":5.6836134692}
{"dobra":0,"indice":232,"SI-SDR_media_foreground_background":5.741610527,"foreground.SI-SDR":7.0889677222,"background.SI-SDR":4.3942533456}
{"dobra":0,"indice":234,"SI-SDR_media_foreground_background":9.5285272598,"foreground.SI-SDR":9.1865782649,"background.SI-SDR":9.8704766699}
{"dobra":1,"indice":5,"SI-SDR_media_foreground_background":4.4501605034,"foreground.SI-SDR":1.9935064157,"background.SI-SDR":6.9068150275}
{"dobra":1,"indice":14,"SI-SDR_media_foreground_background":2.3916101456,"foreground.SI-SDR":-3.0567143889,"background.SI-SDR":7.8399345846}
{"dobra":1,"indice":16,"SI-SDR_media_foreground_background":2.3390078545,"foreground.SI-SDR":5.6663981836,"background.SI-SDR":-0.9883825371}
{"dobra":1,"indice":17,"SI-SDR_media_foreground_background":2.6386945248,"foreground.SI-SDR":0.3092772971,"background.SI-SDR":4.9681118}
{"dobra":1,"indice":21,"SI-SDR_media_foreground_background":2.1891739368,"foreground.SI-SDR":-0.0703207674,"background.SI-SDR":4.4486687573}
{"dobra":1,"indice":27,"SI-SDR_media_foreground_background":9.5204734802,"foreground.SI-SDR":7.0306440764,"background.SI-SDR":12.0103024005}
{"dobra":1,"indice":28,"SI-SDR_media_foreground_background":-2.5050060749,"foreground.SI-SDR":2.9474952825,"background.SI-SDR":-7.9575076057}
{"dobra":1,"indice":40,"SI-SDR_media_foreground_background":0.8294841647,"foreground.SI-SDR":-0.286303719,"background.SI-SDR":1.9452720452}
{"dobra":1,"indice":42,"SI-SDR_media_foreground_background":3.8424079418,"foreground.SI-SDR":4.0922406847,"background.SI-SDR":3.5925751062}
{"dobra":1,"indice":47,"SI-SDR_media_foreground_background":1.7002489567,"foreground.SI-SDR":-4.1067058235,"background.SI-SDR":7.5072037421}
{"dobra":1,"indice":53,"SI-SDR_media_foreground_background":0.4655838609,"foreground.SI-SDR":3.3473097509,"background.SI-SDR":-2.4161420319}
{"dobra":1,"indice":55,"SI-SDR_media_foreground_background":7.5864262581,"foreground.SI-SDR":6.2842851882,"background.SI-SDR":8.8885677354}
{"dobra":1,"indice":56,"SI-SDR_media_foreground_background":0.3301548064,"foreground.SI-SDR":-1.9830351087,"background.SI-SDR":2.6433447098}
{"dobra":1,"indice":59,"SI-SDR_media_foreground_background":2.8593387604,"foreground.SI-SDR":2.2066346677,"background.SI-SDR":3.512042773}
{"dobra":1,"indice":73,"SI-SDR_media_foreground_background":4.8854346275,"foreground.SI-SDR":0.7213522886,"background.SI-SDR":9.0495169424}
{"dobra":1,"indice":84,"SI-SDR_media_foreground_background":8.4170846939,"foreground.SI-SDR":6.7173687261,"background.SI-SDR":10.1167999129}
{"dobra":1,"indice":85,"SI-SDR_media_foreground_background":2.592574358,"foreground.SI-SDR":-0.508083916,"background.SI-SDR":5.6932324459}
{"dobra":1,"indice":90,"SI-SDR_media_foreground_background":7.1418571472,"foreground.SI-SDR":10.3628995239,"background.SI-SDR":3.9208145922}
{"dobra":1,"indice":93,"SI-SDR_media_foreground_background":3.3635175228,"foreground.SI-SDR":-0.4078596843,"background.SI-SDR":7.134894629}
{"dobra":1,"indice":95,"SI-SDR_media_foreground_background":3.4238321781,"foreground.SI-SDR":1.8559399808,"background.SI-SDR":4.9917244916}
{"dobra":1,"indice":99,"SI-SDR_media_foreground_background":-1.4214959145,"foreground.SI-SDR":-2.7733962552,"background.SI-SDR":-0.0695955415}
{"dobra":1,"indice":107,"SI-SDR_media_foreground_background":7.5611143112,"foreground.SI-SDR":3.6421464629,"background.SI-SDR":11.4800820373}
{"dobra":1,"indice":108,"SI-SDR_media_foreground_background":0.9954152703,"foreground.SI-SDR":-4.9653317511,"background.SI-SDR":6.9561623438}
{"dobra":1,"indice":110,"SI-SDR_media_foreground_background":3.4670267105,"foreground.SI-SDR":0.5939846836,"background.SI-SDR":6.3400686559}
{"dobra":1,"indice":117,"SI-SDR_media_foreground_background":3.9657509327,"foreground.SI-SDR":2.1255362035,"background.SI-SDR":5.8059658077}
{"dobra":1,"indice":123,"SI-SDR_media_foreground_background":1.5548083782,"foreground.SI-SDR":-4.2675079604,"background.SI-SDR":7.377124775}
{"dobra":1,"indice":127,"SI-SDR_media_foreground_background":3.8218092918,"foreground.SI-SDR":0.4223083682,"background.SI-SDR":7.2213104359}
{"dobra":1,"indice":130,"SI-SDR_media_foreground_background":3.47286129,"foreground.SI-SDR":0.9372824283,"background.SI-SDR":6.0084399866}
{"dobra":1,"indice":159,"SI-SDR_media_foreground_background":8.056014061,"foreground.SI-SDR":6.0840646885,"background.SI-SDR":10.0279635443}
{"dobra":1,"indice":163,"SI-SDR_media_foreground_background":4.5774927139,"foreground.SI-SDR":4.2282696633,"background.SI-SDR":4.926715447}
{"dobra":1,"indice":164,"SI-SDR_media_foreground_background":2.5524787903,"foreground.SI-SDR":4.7573764749,"background.SI-SDR":0.3475811976}
{"dobra":1,"indice":167,"SI-SDR_media_foreground_background":3.5863287449,"foreground.SI-SDR":1.9501740948,"background.SI-SDR":5.2224835729}
{"dobra":1,"indice":168,"SI-SDR_media_foreground_background":6.5289440155,"foreground.SI-SDR":2.3053404818,"background.SI-SDR":10.7525473022}
{"dobra":1,"indice":170,"SI-SDR_media_foreground_background":-0.8716984987,"foreground.SI-SDR":3.1780158559,"background.SI-SDR":-4.9214129094}
{"dobra":1,"indice":173,"SI-SDR_media_foreground_background":4.8204479218,"foreground.SI-SDR":8.6322148907,"background.SI-SDR":1.0086808786}
{"dobra":1,"indice":176,"SI-SDR_media_foreground_background":7.2200684547,"foreground.SI-SDR":4.296825994,"background.SI-SDR":10.1433105305}
{"dobra":1,"indice":180,"SI-SDR_media_foreground_background":6.683028698,"foreground.SI-SDR":-0.4572702323,"background.SI-SDR":13.8233277813}
{"dobra":1,"indice":188,"SI-SDR_media_foreground_background":6.2285051346,"foreground.SI-SDR":3.1602258871,"background.SI-SDR":9.2967846898}
{"dobra":1,"indice":194,"SI-SDR_media_foreground_background":0.8119445443,"foreground.SI-SDR":-0.7980460958,"background.SI-SDR":2.4219351293}
{"dobra":1,"indice":206,"SI-SDR_media_foreground_background":3.1140339375,"foreground.SI-SDR":-3.8050131112,"background.SI-SDR":10.0330810575}
{"dobra":1,"indice":215,"SI-SDR_media_foreground_background":9.7030735016,"foreground.SI-SDR":8.4408486144,"background.SI-SDR":10.9652977}
{"dobra":1,"indice":217,"SI-SDR_media_foreground_background":5.5761175156,"foreground.SI-SDR":1.0387467373,"background.SI-SDR":10.1134879253}
{"dobra":1,"indice":224,"SI-SDR_media_foreground_background":5.6116714478,"foreground.SI-SDR":2.3444138,"background.SI-SDR":8.8789287486}
{"dobra":1,"indice":226,"SI-SDR_media_foreground_background":2.7383775711,"foreground.SI-SDR":-1.05544561,"background.SI-SDR":6.5322009505}
{"dobra":1,"indice":228,"SI-SDR_media_foreground_background":4.4614343643,"foreground.SI-SDR":-2.9560792582,"background.SI-SDR":11.8789476425}
{"dobra":1,"indice":229,"SI-SDR_media_foreground_background":11.3834056854,"foreground.SI-SDR":6.5747405728,"background.SI-SDR":16.1920706786}
{"dobra":1,"indice":230,"SI-SDR_media_foreground_background":5.0909256935,"foreground.SI-SDR":5.3533697966,"background.SI-SDR":4.8284819231}
{"dobra":2,"indice":12,"SI-SDR_media_foreground_background":5.902674675,"foreground.SI-SDR":5.4562418088,"background.SI-SDR":6.3491071234}
{"dobra":2,"indice":13,"SI-SDR_media_foreground_background":5.5796751976,"foreground.SI-SDR":5.0915593406,"background.SI-SDR":6.0677909357}
{"dobra":2,"indice":36,"SI-SDR_media_foreground_background":4.4005537033,"foreground.SI-SDR":-1.7313837435,"background.SI-SDR":10.5324909722}
{"dobra":2,"indice":45,"SI-SDR_media_foreground_background":6.605383873,"foreground.SI-SDR":6.2952668284,"background.SI-SDR":6.9155005438}
{"dobra":2,"indice":48,"SI-SDR_media_foreground_background":7.1542344093,"foreground.SI-SDR":0.4087211909,"background.SI-SDR":13.8997478968}
{"dobra":2,"indice":54,"SI-SDR_media_foreground_background":3.7305703163,"foreground.SI-SDR":-0.7433209918,"background.SI-SDR":8.2044614832}
{"dobra":2,"indice":66,"SI-SDR_media_foreground_background":2.9922053814,"foreground.SI-SDR":0.2567899089,"background.SI-SDR":5.7276210541}
{"dobra":2,"indice":70,"SI-SDR_media_foreground_background":1.4870530367,"foreground.SI-SDR":-1.5589825478,"background.SI-SDR":4.5330885374}
{"dobra":2,"indice":75,"SI-SDR_media_foreground_background":6.7272286415,"foreground.SI-SDR":1.8742973069,"background.SI-SDR":11.5801601432}
{"dobra":2,"indice":81,"SI-SDR_media_foreground_background":4.5381522179,"foreground.SI-SDR":-1.4319397757,"background.SI-SDR":10.5082439144}
{"dobra":2,"indice":82,"SI-SDR_media_foreground_background":4.8380250931,"foreground.SI-SDR":6.1500615162,"background.SI-SDR":3.5259885824}
{"dobra":2,"indice":94,"SI-SDR_media_foreground_background":2.7647242546,"foreground.SI-SDR":1.5113304774,"background.SI-SDR":4.0181181277}
{"dobra":2,"indice":97,"SI-SDR_media_foreground_background":7.9673171043,"foreground.SI-SDR":7.8050823304,"background.SI-SDR":8.1295519487}
{"dobra":2,"indice":98,"SI-SDR_media_foreground_background":3.6397135258,"foreground.SI-SDR":0.600660877,"background.SI-SDR":6.6787660543}
{"dobra":2,"indice":102,"SI-SDR_media_foreground_background":3.7144663334,"foreground.SI-SDR":7.971859052,"background.SI-SDR":-0.5429264959}
{"dobra":2,"indice":103,"SI-SDR_media_foreground_background":0.4515227675,"foreground.SI-SDR":2.4946973931,"background.SI-SDR":-1.5916518774}
{"dobra":2,"indice":105,"SI-SDR_media_foreground_background":5.7355966568,"foreground.SI-SDR":3.7185513429,"background.SI-SDR":7.7526419854}
{"dobra":2,"indice":118,"SI-SDR_media_foreground_background":5.1085157394,"foreground.SI-SDR":2.4571993513,"background.SI-SDR":7.7598324966}
{"dobra":2,"indice":120,"SI-SDR_media_foreground_background":5.2718224525,"foreground.SI-SDR":2.8656733535,"background.SI-SDR":7.6779719419}
{"dobra":2,"indice":124,"SI-SDR_media_foreground_background":8.7377967834,"foreground.SI-SDR":7.9367762643,"background.SI-SDR":9.5388170705}
{"dobra":2,"indice":132,"SI-SDR_media_foreground_background":3.8963274956,"foreground.SI-SDR":-1.7734276697,"background.SI-SDR":9.5660824811}
{"dobra":2,"indice":145,"SI-SDR_media_foreground_background":6.185693264,"foreground.SI-SDR":3.6249230444,"background.SI-SDR":8.746463305}
{"dobra":2,"indice":147,"SI-SDR_media_foreground_background":0.0539355837,"foreground.SI-SDR":-4.7677209741,"background.SI-SDR":4.8755921439}
{"dobra":2,"indice":151,"SI-SDR_media_foreground_background":3.6805241108,"foreground.SI-SDR":5.297670431,"background.SI-SDR":2.0633778711}
{"dobra":2,"indice":152,"SI-SDR_media_foreground_background":7.2235794067,"foreground.SI-SDR":4.2542611024,"background.SI-SDR":10.1928980912}
{"dobra":2,"indice":158,"SI-SDR_media_foreground_background":5.8035778999,"foreground.SI-SDR":6.1713803586,"background.SI-SDR":5.4357755964}
{"dobra":2,"indice":161,"SI-SDR_media_foreground_background":2.1832518578,"foreground.SI-SDR":0.7185618673,"background.SI-SDR":3.647941846}
{"dobra":2,"indice":166,"SI-SDR_media_foreground_background":4.0996451378,"foreground.SI-SDR":1.9268417948,"background.SI-SDR":6.2724482614}
{"dobra":2,"indice":172,"SI-SDR_media_foreground_background":6.7841424942,"foreground.SI-SDR":2.5768833784,"background.SI-SDR":10.9914013351}
{"dobra":2,"indice":179,"SI-SDR_media_foreground_background":6.6224012375,"foreground.SI-SDR":7.1982609947,"background.SI-SDR":6.0465411598}
{"dobra":2,"indice":184,"SI-SDR_media_foreground_background":5.9341216087,"foreground.SI-SDR":3.0194742561,"background.SI-SDR":8.8487692431}
{"dobra":2,"indice":185,"SI-SDR_media_foreground_background":5.9492983818,"foreground.SI-SDR":1.8485176968,"background.SI-SDR":10.0500787873}
{"dobra":2,"indice":189,"SI-SDR_media_foreground_background":3.3073816299,"foreground.SI-SDR":1.2716511368,"background.SI-SDR":5.3431122302}
{"dobra":2,"indice":190,"SI-SDR_media_foreground_background":4.3953838348,"foreground.SI-SDR":-2.5292816642,"background.SI-SDR":11.3200492631}
{"dobra":2,"indice":191,"SI-SDR_media_foreground_background":5.5491633415,"foreground.SI-SDR":5.3223007272,"background.SI-SDR":5.7760264137}
{"dobra":2,"indice":193,"SI-SDR_media_foreground_background":6.4502668381,"foreground.SI-SDR":5.1512908813,"background.SI-SDR":7.7492426366}
{"dobra":2,"indice":196,"SI-SDR_media_foreground_background":3.1359372139,"foreground.SI-SDR":1.854068286,"background.SI-SDR":4.4178062903}
{"dobra":2,"indice":198,"SI-SDR_media_foreground_background":3.1343195438,"foreground.SI-SDR":3.1723543556,"background.SI-SDR":3.0962849348}
{"dobra":2,"indice":205,"SI-SDR_media_foreground_background":0.9130449891,"foreground.SI-SDR":-4.1893133785,"background.SI-SDR":6.0154033499}
{"dobra":2,"indice":208,"SI-SDR_media_foreground_background":2.5492503643,"foreground.SI-SDR":0.6881198415,"background.SI-SDR":4.4103810125}
{"dobra":2,"indice":209,"SI-SDR_media_foreground_background":3.3948094845,"foreground.SI-SDR":2.5185506919,"background.SI-SDR":4.271068261}
{"dobra":2,"indice":213,"SI-SDR_media_foreground_background":3.301158905,"foreground.SI-SDR":-0.7275528704,"background.SI-SDR":7.3298707503}
{"dobra":2,"indice":214,"SI-SDR_media_foreground_background":6.9559512138,"foreground.SI-SDR":2.9939245579,"background.SI-SDR":10.9179780114}
{"dobra":2,"indice":216,"SI-SDR_media_foreground_background":5.5184111595,"foreground.SI-SDR":4.6720331183,"background.SI-SDR":6.3647890312}
{"dobra":2,"indice":219,"SI-SDR_media_foreground_background":3.0831577778,"foreground.SI-SDR":6.1929934465,"background.SI-SDR":-0.0266779513}
{"dobra":2,"indice":227,"SI-SDR_media_foreground_background":5.9208483696,"foreground.SI-SDR":5.9387626239,"background.SI-SDR":5.9029345217}
{"dobra":2,"indice":233,"SI-SDR_media_foreground_background":5.1840257645,"foreground.SI-SDR":2.3108563262,"background.SI-SDR":8.0571950408}
{"dobra":3,"indice":2,"SI-SDR_media_foreground_background":3.9509894848,"foreground.SI-SDR":1.5169681221,"background.SI-SDR":6.3850109694}
{"dobra":3,"indice":3,"SI-SDR_media_foreground_background":4.4753751755,"foreground.SI-SDR":0.4074040906,"background.SI-SDR":8.5433462862}
{"dobra":3,"indice":6,"SI-SDR_media_foreground_background":3.2959361076,"foreground.SI-SDR":-0.5279178145,"background.SI-SDR":7.1197899383}
{"dobra":3,"indice":9,"SI-SDR_media_foreground_background":5.7867159843,"foreground.SI-SDR":4.9210841847,"background.SI-SDR":6.6523479728}
{"dobra":3,"indice":10,"SI-SDR_media_foreground_background":2.7427852154,"foreground.SI-SDR":-0.9133210066,"background.SI-SDR":6.3988914179}
{"dobra":3,"indice":15,"SI-SDR_media_foreground_background":3.5362658501,"foreground.SI-SDR":3.3410066257,"background.SI-SDR":3.7315248455}
{"dobra":3,"indice":23,"SI-SDR_media_foreground_background":3.4998278618,"foreground.SI-SDR":-1.5664167574,"background.SI-SDR":8.5660723262}
{"dobra":3,"indice":24,"SI-SDR_media_foreground_background":4.315823555,"foreground.SI-SDR":-3.9688174616,"background.SI-SDR":12.6004647356}
{"dobra":3,"indice":26,"SI-SDR_media_foreground_background":6.6994771957,"foreground.SI-SDR":5.5037365439,"background.SI-SDR":7.8952175014}
{"dobra":3,"indice":32,"SI-SDR_media_foreground_background":3.2564313412,"foreground.SI-SDR":-0.8889924648,"background.SI-SDR":7.4018553585}
{"dobra":3,"indice":41,"SI-SDR_media_foreground_background":-26.1467514038,"foreground.SI-SDR":5.8821106545,"background.SI-SDR":-58.1756143749}
{"dobra":3,"indice":43,"SI-SDR_media_foreground_background":6.7473387718,"foreground.SI-SDR":3.1745604758,"background.SI-SDR":10.3201172271}
{"dobra":3,"indice":46,"SI-SDR_media_foreground_background":6.9169335365,"foreground.SI-SDR":4.076517917,"background.SI-SDR":9.7573488896}
{"dobra":3,"indice":52,"SI-SDR_media_foreground_background":2.108574152,"foreground.SI-SDR":-3.9541488382,"background.SI-SDR":8.1712973492}
{"dobra":3,"indice":64,"SI-SDR_media_foreground_background":5.8753714561,"foreground.SI-SDR":2.8540989087,"background.SI-SDR":8.8966443296}
{"dobra":3,"indice":65,"SI-SDR_media_foreground_background":5.1031322479,"foreground.SI-SDR":0.9157857863,"background.SI-SDR":9.2904787945}
{"dobra":3,"indice":74,"SI-SDR_media_foreground_background":2.0412123203,"foreground.SI-SDR":-0.7150203731,"background.SI-SDR":4.7974448721}
{"dobra":3,"indice":76,"SI-SDR_media_foreground_background":3.8015208244,"foreground.SI-SDR":3.1734748578,"background.SI-SDR":4.4295670088}
{"dobra":3,"indice":77,"SI-SDR_media_foreground_background":7.1714706421,"foreground.SI-SDR":3.2314731351,"background.SI-SDR":11.1114685602}
{"dobra":3,"indice":80,"SI-SDR_media_foreground_background":3.7899608612,"foreground.SI-SDR":3.8959446375,"background.SI-SDR":3.6839768696}
{"dobra":3,"indice":83,"SI-SDR_media_foreground_background":-2.0765862465,"foreground.SI-SDR":-1.8030069205,"background.SI-SDR":-2.3501657739}
{"dobra":3,"indice":87,"SI-SDR_media_foreground_background":7.0786981583,"foreground.SI-SDR":4.0794007622,"background.SI-SDR":10.0779956582}
{"dobra":3,"indice":92,"SI-SDR_media_foreground_background":6.2602362633,"foreground.SI-SDR":3.0516466365,"background.SI-SDR":9.4688260814}
{"dobra":3,"indice":100,"SI-SDR_media_foreground_background":2.9406762123,"foreground.SI-SDR":0.8547511851,"background.SI-SDR":5.0266012471}
{"dobra":3,"indice":104,"SI-SDR_media_foreground_background":1.1384356022,"foreground.SI-SDR":2.4091078376,"background.SI-SDR":-0.1322366928}
{"dobra":3,"indice":109,"SI-SDR_media_foreground_background":13.1242828369,"foreground.SI-SDR":10.301431522,"background.SI-SDR":15.9471351036}
{"dobra":3,"indice":111,"SI-SDR_media_foreground_background":7.4084439278,"foreground.SI-SDR":7.4548866555,"background.SI-SDR":7.3620013443}
{"dobra":3,"indice":113,"SI-SDR_media_foreground_background":4.8653945923,"foreground.SI-SDR":2.5772638798,"background.SI-SDR":7.1535250366}
{"dobra":3,"indice":125,"SI-SDR_media_foreground_background":3.2842979431,"foreground.SI-SDR":-1.3245065239,"background.SI-SDR":7.8931024221}
{"dobra":3,"indice":126,"SI-SDR_media_foreground_background":0.2933810353,"foreground.SI-SDR":0.2528231844,"background.SI-SDR":0.3339389104}
{"dobra":3,"indice":135,"SI-SDR_media_foreground_background":7.0777230263,"foreground.SI-SDR":5.0468898549,"background.SI-SDR":9.1085566355}
{"dobra":3,"indice":136,"SI-SDR_media_foreground_background":5.6742677689,"foreground.SI-SDR":3.2294901982,"background.SI-SDR":8.1190453903}
{"dobra":3,"indice":143,"SI-SDR_media_foreground_background":5.5811796188,"foreground.SI-SDR":4.0708225461,"background.SI-SDR":7.0915369679}
{"dobra":3,"indice":153,"SI-SDR_media_foreground_background":4.6122202873,"foreground.SI-SDR":0.76099029,"background.SI-SDR":8.4634505597}
{"dobra":3,"indice":155,"SI-SDR_media_foreground_background":7.3527708054,"foreground.SI-SDR":4.9265448034,"background.SI-SDR":9.7789966774}
{"dobra":3,"indice":165,"SI-SDR_media_foreground_background":3.089584589,"foreground.SI-SDR":-1.7739258384,"background.SI-SDR":7.9530949446}
{"dobra":3,"indice":174,"SI-SDR_media_foreground_background":3.9811780453,"foreground.SI-SDR":2.121215564,"background.SI-SDR":5.8411403833}
{"dobra":3,"indice":181,"SI-SDR_media_foreground_background":6.1790828705,"foreground.SI-SDR":2.0902655521,"background.SI-SDR":10.2679006301}
{"dobra":3,"indice":182,"SI-SDR_media_foreground_background":5.1936368942,"foreground.SI-SDR":3.3841340199,"background.SI-SDR":7.0031402328}
{"dobra":3,"indice":183,"SI-SDR_media_foreground_background":9.0470247269,"foreground.SI-SDR":7.2147963598,"background.SI-SDR":10.8792529452}
{"dobra":3,"indice":186,"SI-SDR_media_foreground_background":5.5782008171,"foreground.SI-SDR":3.8308358783,"background.SI-SDR":7.3255654215}
{"dobra":3,"indice":187,"SI-SDR_media_foreground_background":5.0286440849,"foreground.SI-SDR":2.5557407238,"background.SI-SDR":7.5015473889}
{"dobra":3,"indice":195,"SI-SDR_media_foreground_background":2.0992763042,"foreground.SI-SDR":0.6875995864,"background.SI-SDR":3.5109532181}
{"dobra":3,"indice":199,"SI-SDR_media_foreground_background":5.780728817,"foreground.SI-SDR":2.6654339882,"background.SI-SDR":8.8960236718}
{"dobra":3,"indice":201,"SI-SDR_media_foreground_background":0.8074936867,"foreground.SI-SDR":-3.1337084205,"background.SI-SDR":4.748695745}
{"dobra":3,"indice":202,"SI-SDR_media_foreground_background":5.338019371,"foreground.SI-SDR":0.5261690984,"background.SI-SDR":10.1498695376}
{"dobra":3,"indice":221,"SI-SDR_media_foreground_background":2.7781040668,"foreground.SI-SDR":-0.9062252359,"background.SI-SDR":6.4624335301}
{"dobra":4,"indice":1,"SI-SDR_media_foreground_background":-1.2443854809,"foreground.SI-SDR":-2.5174769658,"background.SI-SDR":0.0287060801}
{"dobra":4,"indice":7,"SI-SDR_media_foreground_background":4.2263636589,"foreground.SI-SDR":3.0852954321,"background.SI-SDR":5.3674322137}
{"dobra":4,"indice":8,"SI-SDR_media_foreground_background":7.2042460442,"foreground.SI-SDR":2.7435023933,"background.SI-SDR":11.6649895213}
{"dobra":4,"indice":20,"SI-SDR_media_foreground_background":2.8750679493,"foreground.SI-SDR":-0.3138050617,"background.SI-SDR":6.0639410128}
{"dobra":4,"indice":22,"SI-SDR_media_foreground_background":5.629421711,"foreground.SI-SDR":5.4733764164,"background.SI-SDR":5.785466957}
{"dobra":4,"indice":25,"SI-SDR_media_foreground_background":4.6040873528,"foreground.SI-SDR":-0.765501883,"background.SI-SDR":9.9736769986}
{"dobra":4,"indice":30,"SI-SDR_media_foreground_background":4.9641041756,"foreground.SI-SDR":3.2574790728,"background.SI-SDR":6.6707294262}
{"dobra":4,"indice":37,"SI-SDR_media_foreground_background":5.4791054726,"foreground.SI-SDR":-1.7027075271,"background.SI-SDR":12.6609182961}
{"dobra":4,"indice":49,"SI-SDR_media_foreground_background":2.6652743816,"foreground.SI-SDR":-1.9240008684,"background.SI-SDR":7.2545496805}
{"dobra":4,"indice":50,"SI-SDR_media_foreground_background":6.6528406143,"foreground.SI-SDR":2.8379662926,"background.SI-SDR":10.4677153862}
{"dobra":4,"indice":57,"SI-SDR_media_foreground_background":5.6882429123,"foreground.SI-SDR":0.0261830508,"background.SI-SDR":11.3503030408}
{"dobra":4,"indice":60,"SI-SDR_media_foreground_background":7.2707214355,"foreground.SI-SDR":5.4525396719,"background.SI-SDR":9.0889032044}
{"dobra":4,"indice":61,"SI-SDR_media_foreground_background":3.980332613,"foreground.SI-SDR":-1.4493345815,"background.SI-SDR":9.4099999048}
{"dobra":4,"indice":63,"SI-SDR_media_foreground_background":-0.7758864164,"foreground.SI-SDR":-1.8919695368,"background.SI-SDR":0.3401967034}
{"dobra":4,"indice":68,"SI-SDR_media_foreground_background":1.1832596064,"foreground.SI-SDR":1.9423409633,"background.SI-SDR":0.4241781756}
{"dobra":4,"indice":71,"SI-SDR_media_foreground_background":5.3899846077,"foreground.SI-SDR":1.4509864712,"background.SI-SDR":9.3289829954}
{"dobra":4,"indice":72,"SI-SDR_media_foreground_background":6.2949476242,"foreground.SI-SDR":4.0118742513,"background.SI-SDR":8.5780211114}
{"dobra":4,"indice":79,"SI-SDR_media_foreground_background":12.6761903763,"foreground.SI-SDR":9.7694334766,"background.SI-SDR":15.5829468263}
{"dobra":4,"indice":86,"SI-SDR_media_foreground_background":5.3275785446,"foreground.SI-SDR":1.0133117976,"background.SI-SDR":9.6418449203}
{"dobra":4,"indice":96,"SI-SDR_media_foreground_background":4.359231472,"foreground.SI-SDR":1.1466584362,"background.SI-SDR":7.571804274}
{"dobra":4,"indice":101,"SI-SDR_media_foreground_background":3.8645603657,"foreground.SI-SDR":5.8902855316,"background.SI-SDR":1.8388350087}
{"dobra":4,"indice":115,"SI-SDR_media_foreground_background":3.8074645996,"foreground.SI-SDR":1.4721290709,"background.SI-SDR":6.1428001639}
{"dobra":4,"indice":121,"SI-SDR_media_foreground_background":3.3599624634,"foreground.SI-SDR":-1.0399244549,"background.SI-SDR":7.7598494415}
{"dobra":4,"indice":128,"SI-SDR_media_foreground_background":4.6591043472,"foreground.SI-SDR":3.3809286158,"background.SI-SDR":5.9372805338}
{"dobra":4,"indice":129,"SI-SDR_media_foreground_background":5.6194086075,"foreground.SI-SDR":0.3979074059,"background.SI-SDR":10.8409097409}
{"dobra":4,"indice":131,"SI-SDR_media_foreground_background":5.0745835304,"foreground.SI-SDR":4.5810956076,"background.SI-SDR":5.5680713565}
{"dobra":4,"indice":133,"SI-SDR_media_foreground_background":4.3731460571,"foreground.SI-SDR":0.0567579345,"background.SI-SDR":8.6895339484}
{"dobra":4,"indice":134,"SI-SDR_media_foreground_background":3.2647736073,"foreground.SI-SDR":-0.9857009917,"background.SI-SDR":7.5152484186}
{"dobra":4,"indice":137,"SI-SDR_media_foreground_background":3.4846887589,"foreground.SI-SDR":0.675371942,"background.SI-SDR":6.2940054635}
{"dobra":4,"indice":139,"SI-SDR_media_foreground_background":1.2325000763,"foreground.SI-SDR":-2.5694170846,"background.SI-SDR":5.0344171204}
{"dobra":4,"indice":140,"SI-SDR_media_foreground_background":3.3030512333,"foreground.SI-SDR":0.2386814225,"background.SI-SDR":6.3674211903}
{"dobra":4,"indice":141,"SI-SDR_media_foreground_background":0.3402970731,"foreground.SI-SDR":1.8562276152,"background.SI-SDR":-1.1756334702}
{"dobra":4,"indice":142,"SI-SDR_media_foreground_background":3.6757736206,"foreground.SI-SDR":-0.3781985647,"background.SI-SDR":7.7297460252}
{"dobra":4,"indice":144,"SI-SDR_media_foreground_background":6.9199967384,"foreground.SI-SDR":4.0923427823,"background.SI-SDR":9.7476502404}
{"dobra":4,"indice":146,"SI-SDR_media_foreground_background":2.6137859821,"foreground.SI-SDR":-3.4271225211,"background.SI-SDR":8.6546946963}
{"dobra":4,"indice":149,"SI-SDR_media_foreground_background":5.9409503937,"foreground.SI-SDR":2.2230488727,"background.SI-SDR":9.6588516287}
{"dobra":4,"indice":156,"SI-SDR_media_foreground_background":5.9575986862,"foreground.SI-SDR":3.491746741,"background.SI-SDR":8.4234503876}
{"dobra":4,"indice":157,"SI-SDR_media_foreground_background":7.2456784248,"foreground.SI-SDR":5.0610559273,"background.SI-SDR":9.4303012588}
{"dobra":4,"indice":175,"SI-SDR_media_foreground_background":4.5193099976,"foreground.SI-SDR":0.8870360487,"background.SI-SDR":8.1515840934}
{"dobra":4,"indice":178,"SI-SDR_media_foreground_background":3.9332337379,"foreground.SI-SDR":-3.5593809745,"background.SI-SDR":11.4258484614}
{"dobra":4,"indice":192,"SI-SDR_media_foreground_background":3.9030125141,"foreground.SI-SDR":-4.4212613809,"background.SI-SDR":12.2272861799}
{"dobra":4,"indice":203,"SI-SDR_media_foreground_background":6.4481244087,"foreground.SI-SDR":3.7204113532,"background.SI-SDR":9.1758371757}
{"dobra":4,"indice":204,"SI-SDR_media_foreground_background":5.683614254,"foreground.SI-SDR":3.5681422972,"background.SI-SDR":7.79908596}
{"dobra":4,"indice":207,"SI-SDR_media_foreground_background":-2.1695113182,"foreground.SI-SDR":-10.9447348199,"background.SI-SDR":6.6057121146}
{"dobra":4,"indice":212,"SI-SDR_media_foreground_background":8.6889772415,"foreground.SI-SDR":5.8097922366,"background.SI-SDR":11.5681617007}
{"dobra":4,"indice":223,"SI-SDR_media_foreground_background":5.4321913719,"foreground.SI-SDR":2.9203397443,"background.SI-SDR":7.944042708}
{"dobra":4,"indice":231,"SI-SDR_media_foreground_background":3.7839958668,"foreground.SI-SDR":-1.8310281266,"background.SI-SDR":9.3990197731}
